DotaCLI-1.0.0.dist-info/entry_points.txt
DotaCLI-1.0.0.dist-info/METADATA
DotaCLI-1.0.0.dist-info/metadata.json
DotaCLI-1.0.0.dist-info/top_level.txt
DotaCLI-1.0.0.dist-info/WHEEL
DotaCLI-1.0.0.dist-info/DESCRIPTION.rst
DotaCLI-1.0.0.dist-info/RECORD
Diretide/__init__.py
Diretide/lib.py
Diretide/info.py
Diretide/app.py
