Metadata-Version: 2.0
Name: DotaCLI
Version: 1.0.0
Summary: Check Dota 2 Match schedule from the CLI
Home-page: https://bitbucket.org/GodHand/dotacli
Author: Steven L
Author-email: leibrockoli@gmail.com
License: MIT
Keywords: dota2 dota 2 livestreamer twitch games cli
Platform: UNKNOWN
Classifier: Development Status :: 5 - Production/Stable
Classifier: Intended Audience :: Developers
Classifier: Programming Language :: Python :: 2
Classifier: Programming Language :: Python :: 2.6
Classifier: Programming Language :: Python :: 2.7
Classifier: Programming Language :: Python :: 3
Classifier: Programming Language :: Python :: 3.2
Classifier: Programming Language :: Python :: 3.3
Classifier: Programming Language :: Python :: 3.4
Requires-Dist: requests
